{
  "title": "",
  "why": "",
  "impact": "",
  "next_steps": [],
  "text": "# 🎯 POPDOG İÇİN BUGÜN ALINCAK EN ÖNEMLİ KARAR\n\n## **ENVENTERİ KRİZİNİ DERHAL ÇÖZÜN**\n\n### 🚨 Kritik Sorun:\n\"Küçük Bakım 0-5 KG\" ürünü **-11 stok** (negatif!)\n- Müşteriler sipariş veriyor, teslimat yapılamıyor\n- Müşteri memnuniyeti düşüyor\n- İtibara zarar veriyor\n\n### 📊 Bağlam:\n- **91 sipariş** son 7 günde ✅ (Satış çok iyi)\n- **Mobile trafiği %91** (Ana kanal)\n- **Meta DPA kampanyası** 19x ROAS (En iyi performer)\n- Ama **stok yönetimi çökmüş**\n\n---\n\n## ✅ BUGÜN YAPILACAKLAR (Sırası ile):\n\n1. **Şimdi:** \"Küçük Bakım 0-5 KG\" ürünü siteden kaldır\n2. **1 Saat:** Tedarikçiye acil restock siparişi ver\n3. **2 Saat:** Beklemedeki müşterilere (en az 10+) itibar kredisi/indirim gönder\n4. **Bugün sonu:** Stok yönetim sistemini otomatikleştir\n\n---\n\n## 💡 Neden Bu?\n- Satış momentum çok iyi (kaybedemezsin)\n- Stok sorunu **anında gelir kaybı** + **müşteri kaybı**\n- Diğer ürünler sağlıklı → sadece bu ürünü çöz\n- Meta kampanyaları 14-19x ROAS veriyor → trafik kesilmemesi gerekli\n\n**Başlamak için:** Shopify admin → Ürünler → Bu ürünü devre dışı bırak + tedarikçiye kızıl uyarı gönder.",
  "updated_at": "2026-04-17T02:28:07.609241+00:00"
}